pytsp/__init__.py
pytsp/christofides_tsp.py
pytsp/constants.py
pytsp/had_tsp.py
pytsp/k_opt_tsp.py
pytsp/lin_kerdighan_tsp.py
pytsp/nearest_neighbor_tsp.py
pytsp/permutations_tsp.py
pytsp/pytsp.py
pytsp/utils.py
pytsp/data_structures/__init__.py
pytsp/data_structures/data_structure.py
pytsp/data_structures/opt_case.py
pytsp/genetic_algorithms/__init__.py
pytsp/genetic_algorithms/simulated_annealing.py
pytsp-0.2.4.dist-info/LICENSE
pytsp-0.2.4.dist-info/METADATA
pytsp-0.2.4.dist-info/WHEEL
pytsp-0.2.4.dist-info/top_level.txt
pytsp-0.2.4.dist-info/RECORD
