Metadata-Version: 2.1
Name: pytsp
Version: 0.2.4
Summary: Few algorithms for TSP problem in Python
Home-page: https://github.com/BraveDistribution/pytsp
Author: BraveDistribution
Author-email: gazda.matej@gmail.com
License: MIT license
Keywords: pytsp
Platform: UNKNOWN
Classifier: Development Status :: 2 - Pre-Alpha
Classifier: Intended Audience :: Developers
Classifier: License :: OSI Approved :: MIT License
Classifier: Natural Language :: English
Classifier: Programming Language :: Python :: 3
Classifier: Programming Language :: Python :: 3.4
Classifier: Programming Language :: Python :: 3.5
Classifier: Programming Language :: Python :: 3.6
Classifier: Programming Language :: Python :: 3.7
